s2m/__init__.py
s2m/s2m.py
s2m/s2m_http_server.py
s2m/s2m_min.py
s2m/micro_bit_scripts/s2mb.py
s2m/micro_bit_scripts/s2mb2.py
s2m/micro_bit_scripts/s2mb_min.py
s2m/scratch_files/extensions/s2m.s2e
s2m/scratch_files/extensions/s2m_es.s2e
s2m/scratch_files/extensions/s2m_heb.s2e
s2m/scratch_files/extensions/s2m_ja.s2e
s2m/scratch_files/extensions/s2m_ko.s2e
s2m/scratch_files/extensions/s2m_ptbr.s2e
s2m/scratch_files/extensions/s2m_tw.s2e
s2m/scratch_files/projects/motion_en.sb2
s2m/scratch_files/projects/motion_es.sb2
s2m/scratch_files/projects/motion_ptbr.sb2
s2m/scratch_files/projects/motion_tw.sb2
s2m/scratch_files/projects/s2m.sb2
s2m/scratch_files/projects/s2m_es.sb2
s2m/scratch_files/projects/s2m_heb.sb2
s2m/scratch_files/projects/s2m_ja.sb2
s2m/scratch_files/projects/s2m_ko.sb2
s2m/scratch_files/projects/s2m_ptbr.sb2
s2m/scratch_files/projects/s2m_tw.sb2
s2m-2.11.dist-info/DESCRIPTION.rst
s2m-2.11.dist-info/METADATA
s2m-2.11.dist-info/RECORD
s2m-2.11.dist-info/WHEEL
s2m-2.11.dist-info/entry_points.txt
s2m-2.11.dist-info/metadata.json
s2m-2.11.dist-info/top_level.txt
