Metadata-Version: 2.0
Name: s2m
Version: 2.11
Summary: A Scratch 2.0 (Offline) Hardware Extension for micro:bit
Home-page: https://github.com/MrYsLab/s2m
Author: Alan Yorinks
Author-email: MisterYsLab@gmail.com
License: GNU Affero General Public License v3 (AGPLv3+)
Download-URL: https://github.com/MrYsLab/s2m
Keywords: micro:bit,microbit,Scratch
Platform: UNKNOWN
Classifier: Development Status :: 5 - Production/Stable
Classifier: Environment :: Other Environment
Classifier: Intended Audience :: Education
Classifier: License :: OSI Approved :: GNU Affero General Public License v3 or later (AGPLv3+)
Classifier: Operating System :: OS Independent
Classifier: Programming Language :: Python :: 2.7
Classifier: Programming Language :: Python :: 3.4
Classifier: Programming Language :: Python :: 3.5
Classifier: Programming Language :: Python :: 3.6
Classifier: Topic :: Education
Requires-Dist: pyserial (>=2.7)
Requires-Dist: psutil
